balkongas/__init__.py
balkongas/reactor.py
balkongas-0.1.2.dist-info/METADATA
balkongas-0.1.2.dist-info/WHEEL
balkongas-0.1.2.dist-info/top_level.txt
balkongas-0.1.2.dist-info/RECORD
