Metadata-Version: 2.4
Name: balkongas
Version: 0.1.2
Summary: A Python package for interacting with the balkongas API.
Author-email: Dennis Schwertel <s@digitalkultur.net>
Requires-Python: >=3.7
Provides-Extra: dev
Requires-Dist: pytest; extra == "dev"
Requires-Dist: ruff; extra == "dev"
